dashbase_tools-2.0.2.dist-info/METADATA
dashbase_tools-2.0.2.dist-info/RECORD
dashbase_tools-2.0.2.dist-info/WHEEL
dashbase_tools-2.0.2.dist-info/entry_points.txt
dashbase_tools-2.0.2.dist-info/top_level.txt
tools/__init__.py
tools/dbsql.py
tools/dtail.py
tools/resultview.py
utils/__init__.py
utils/highlight.py
utils/json.py
utils/local_cache.py
utils/parser.py
utils/textwrap.py
