Metadata-Version: 2.1
Name: dashbase-tools
Version: 2.0.2
Summary: UNKNOWN
Home-page: http://www.dashbase.io
Maintainer: khou
Maintainer-email: kevin@dashbase.io
License: UNKNOWN
Platform: UNKNOWN
Requires-Dist: requests
Requires-Dist: dateparser
Requires-Dist: terminaltables
Requires-Dist: schematics
Requires-Dist: colorama
Requires-Dist: pygments
Requires-Dist: dashbase-sdk
Requires-Dist: termcolor
Requires-Dist: simplejson
Requires-Dist: pyyaml
